nemo/__init__.py
nemo/evaluation.py
nemo/graph.py
nemo/precision.py
nemo/relaxation.py
nemo/transform.py
nemo/utils.py
nemo/quant/__init__.py
nemo/quant/pact.py
nemo/transf/__init__.py
nemo/transf/bias.py
nemo/transf/bn.py
nemo/transf/common.py
nemo/transf/deploy.py
nemo/transf/equalize.py
nemo/transf/export.py
nemo/transf/pruning.py
nemo/transf/sawb.py
nemo/transf/statistics.py
nemo/transf/utils.py
pytorch_nemo-0.0.8.dist-info/LICENSE
pytorch_nemo-0.0.8.dist-info/METADATA
pytorch_nemo-0.0.8.dist-info/WHEEL
pytorch_nemo-0.0.8.dist-info/top_level.txt
pytorch_nemo-0.0.8.dist-info/RECORD
