Metadata-Version: 2.1
Name: pytorch-nemo
Version: 0.0.8
Summary: NEural Minimizer for pytOrch
Home-page: https://github.com/pulp-platform/nemo
Author: Francesco Conti
Author-email: f.conti@unibo.it
License: UNKNOWN
Platform: UNKNOWN
Classifier: Programming Language :: Python :: 3
Classifier: License :: OSI Approved :: Apache Software License
Classifier: Operating System :: OS Independent
Requires-Python: >=3.5
Requires-Dist: torch (>=1.3.0)
Requires-Dist: torchvision (>=0.4.1)
Requires-Dist: numpy
Requires-Dist: tqdm
Requires-Dist: packaging
Requires-Dist: scikit-learn
